{
	"id": "e58ca782-17fe-4cc7-a4d1-ffbfae0059a3",
	"name": "Participium Local",
	"values": [
		{
			"key": "baseUrl",
			"value": "",
			"type": "default",
			"enabled": true
		},
		{
			"key": "citizen_email",
			"value": "",
			"type": "default",
			"enabled": true
		},
		{
			"key": "citizen_password",
			"value": "",
			"type": "default",
			"enabled": true
		},
		{
			"key": "operator_email",
			"value": "",
			"type": "default",
			"enabled": true
		},
		{
			"key": "operator_password",
			"value": "",
			"type": "default",
			"enabled": true
		},
		{
			"key": "admin_email",
			"value": "",
			"type": "default",
			"enabled": true
		},
		{
			"key": "admin_password",
			"value": "",
			"type": "default",
			"enabled": true
		},
		{
			"key": "invalid_report_id",
			"value": "",
			"type": "default",
			"enabled": true
		},
		{
			"key": "created_report_id",
			"value": "",
			"type": "default",
			"enabled": true
		},
		{
			"key": "created_category_id",
			"value": "",
			"type": "default",
			"enabled": true
		}
	],
	"color": null,
	"_postman_variable_scope": "environment",
	"_postman_exported_at": "2026-05-07T15:50:01.042Z",
	"_postman_exported_using": "Postman/12.9.2"
}
